[
  {
    "name": "Photo Booth (Digital Only)",
    "slug": "photo-booth-digital-only",
    "price": "500",
    "description": "",
    "guests": null,
    "maxDuration": 3,
    "servicesIncluded": [
      "Photo Booth (Digital Only)"
    ],
    "equipment": [
      "Photo Booth (Digital Only)"
    ],
    "note": "",
    "locations": [
      {
        "location": "Client will provide the address",
        "location_type": "ask"
      }
    ],
    "currency": "CAD",
    "availabilityDays": [
      "Monday",
      "Tuesday",
      "Wednesday",
      "Thursday",
      "Friday",
      "Saturday",
      "Sunday"
    ],
    "startTime": "09:00",
    "endTime": "23:59",
    "eventType": [
      "All"
    ],
    "packageType": "Individual",
    "bookingUrl": "",
    "Sale": "N",
    "New": "N",
    "dateAdded": "07-01-2025",
    "disableGuestsCancelling": true,
    "disableGuestsRescheduling": true,
    "disableCalVideoTranscription": true,
    "disableGuests": true,
    "color": {
      "lightThemeHex": "#292929"
    },
    "minimumBookingNotice": 20160,
    "bookerLayouts": {
      "defaultLayout": "month",
      "enabledLayouts": [
        "month"
      ]
    },
    "bookingFields": [
      {
        "name": "phoneNumber",
        "slug": "phoneNumber",
        "label": "Phone Number",
        "type": "phone",
        "required": true,
        "placeholder": "Please enter your phone number (e.g., +1 123-456-7890)"
      },
      {
        "name": "eventAddress",
        "slug": "eventAddress",
        "label": "Event Address",
        "type": "textarea",
        "required": true,
        "placeholder": "Please enter the full address where the event will take place"
      }
    ],
    "availability": {
      "timeZone": "America/Toronto",
      "schedules": [
        {
          "name": "Availability",
          "timeZone": "America/Toronto",
          "isDefault": true,
          "availability": [
            {
              "days": [
                "Monday",
                "Tuesday",
                "Wednesday",
                "Thursday",
                "Friday",
                "Saturday",
                "Sunday"
              ],
              "startTime": "09:00",
              "endTime": "23:59"
            }
          ]
        }
      ]
    }
  },
  {
    "name": "360 Video Booth",
    "slug": "360-video-booth",
    "price": "600",
    "description": "",
    "guests": null,
    "maxDuration": 3,
    "servicesIncluded": [
      "360 Video Booth"
    ],
    "equipment": [
      "360 Video Booth"
    ],
    "note": "",
    "locations": [
      {
        "location": "Client will provide the address",
        "location_type": "ask"
      }
    ],
    "currency": "CAD",
    "availabilityDays": [
      "Monday",
      "Tuesday",
      "Wednesday",
      "Thursday",
      "Friday",
      "Saturday",
      "Sunday"
    ],
    "startTime": "09:00",
    "endTime": "23:59",
    "eventType": [
      "All"
    ],
    "packageType": "Individual",
    "bookingUrl": "",
    "Sale": "N",
    "New": "N",
    "dateAdded": "07-01-2025",
    "disableGuestsCancelling": true,
    "disableGuestsRescheduling": true,
    "disableCalVideoTranscription": true,
    "disableGuests": true,
    "color": {
      "lightThemeHex": "#292929"
    },
    "minimumBookingNotice": 20160,
    "bookerLayouts": {
      "defaultLayout": "month",
      "enabledLayouts": [
        "month"
      ]
    },
    "bookingFields": [
      {
        "name": "phoneNumber",
        "slug": "phoneNumber",
        "label": "Phone Number",
        "type": "phone",
        "required": true,
        "placeholder": "Please enter your phone number (e.g., +1 123-456-7890)"
      },
      {
        "name": "eventAddress",
        "slug": "eventAddress",
        "label": "Event Address",
        "type": "textarea",
        "required": true,
        "placeholder": "Please enter the full address where the event will take place"
      }
    ],
    "availability": {
      "timeZone": "America/Toronto",
      "schedules": [
        {
          "name": "Availability",
          "timeZone": "America/Toronto",
          "isDefault": true,
          "availability": [
            {
              "days": [
                "Monday",
                "Tuesday",
                "Wednesday",
                "Thursday",
                "Friday",
                "Saturday",
                "Sunday"
              ],
              "startTime": "09:00",
              "endTime": "23:59"
            }
          ]
        }
      ]
    }
  },
  {
    "name": "Audio Guest Book",
    "slug": "audio-guest-book",
    "price": "350",
    "description": "",
    "guests": null,
    "maxDuration": 3,
    "servicesIncluded": [
      "Audio Guest Book"
    ],
    "equipment": [
      "Audio Guest Book"
    ],
    "note": "",
    "locations": [
      {
        "location": "Client will provide the address",
        "location_type": "ask"
      }
    ],
    "currency": "CAD",
    "availabilityDays": [
      "Monday",
      "Tuesday",
      "Wednesday",
      "Thursday",
      "Friday",
      "Saturday",
      "Sunday"
    ],
    "startTime": "09:00",
    "endTime": "23:59",
    "eventType": [
      "All"
    ],
    "packageType": "Individual",
    "bookingUrl": "",
    "Sale": "N",
    "New": "N",
    "dateAdded": "07-01-2025",
    "disableGuestsCancelling": true,
    "disableGuestsRescheduling": true,
    "disableCalVideoTranscription": true,
    "disableGuests": true,
    "color": {
      "lightThemeHex": "#292929"
    },
    "minimumBookingNotice": 20160,
    "bookerLayouts": {
      "defaultLayout": "month",
      "enabledLayouts": [
        "month"
      ]
    },
    "bookingFields": [
      {
        "name": "phoneNumber",
        "slug": "phoneNumber",
        "label": "Phone Number",
        "type": "phone",
        "required": true,
        "placeholder": "Please enter your phone number (e.g., +1 123-456-7890)"
      },
      {
        "name": "eventAddress",
        "slug": "eventAddress",
        "label": "Event Address",
        "type": "textarea",
        "required": true,
        "placeholder": "Please enter the full address where the event will take place"
      }
    ],
    "availability": {
      "timeZone": "America/Toronto",
      "schedules": [
        {
          "name": "Availability",
          "timeZone": "America/Toronto",
          "isDefault": true,
          "availability": [
            {
              "days": [
                "Monday",
                "Tuesday",
                "Wednesday",
                "Thursday",
                "Friday",
                "Saturday",
                "Sunday"
              ],
              "startTime": "09:00",
              "endTime": "23:59"
            }
          ]
        }
      ]
    }
  },
  {
    "name": "Magazine Photo Booth",
    "slug": "magazine-photo-booth",
    "price": "600",
    "description": "",
    "guests": null,
    "maxDuration": 3,
    "servicesIncluded": [
      "Magazine Photo Booth"
    ],
    "equipment": [
      "Magazine Photo Booth"
    ],
    "note": "",
    "locations": [
      {
        "location": "Client will provide the address",
        "location_type": "ask"
      }
    ],
    "currency": "CAD",
    "availabilityDays": [
      "Monday",
      "Tuesday",
      "Wednesday",
      "Thursday",
      "Friday",
      "Saturday",
      "Sunday"
    ],
    "startTime": "09:00",
    "endTime": "23:59",
    "eventType": [
      "All"
    ],
    "packageType": "Individual",
    "bookingUrl": "",
    "Sale": "N",
    "New": "N",
    "dateAdded": "07-01-2025",
    "disableGuestsCancelling": true,
    "disableGuestsRescheduling": true,
    "disableCalVideoTranscription": true,
    "disableGuests": true,
    "color": {
      "lightThemeHex": "#292929"
    },
    "minimumBookingNotice": 20160,
    "bookerLayouts": {
      "defaultLayout": "month",
      "enabledLayouts": [
        "month"
      ]
    },
    "bookingFields": [
      {
        "name": "phoneNumber",
        "slug": "phoneNumber",
        "label": "Phone Number",
        "type": "phone",
        "required": true,
        "placeholder": "Please enter your phone number (e.g., +1 123-456-7890)"
      },
      {
        "name": "eventAddress",
        "slug": "eventAddress",
        "label": "Event Address",
        "type": "textarea",
        "required": true,
        "placeholder": "Please enter the full address where the event will take place"
      }
    ],
    "availability": {
      "timeZone": "America/Toronto",
      "schedules": [
        {
          "name": "Availability",
          "timeZone": "America/Toronto",
          "isDefault": true,
          "availability": [
            {
              "days": [
                "Monday",
                "Tuesday",
                "Wednesday",
                "Thursday",
                "Friday",
                "Saturday",
                "Sunday"
              ],
              "startTime": "09:00",
              "endTime": "23:59"
            }
          ]
        }
      ]
    }
  },
  {
    "name": "Espresso & Coffee Booth",
    "slug": "espresso-and-coffee-booth",
    "price": "50 for 700 | 100 for 1100 | 150 for 1500 | 200 for 1900",
    "description": "",
    "guests": null,
    "maxDuration": 3,
    "servicesIncluded": [
      "Espresso & Coffee Booth"
    ],
    "equipment": [
      "Espresso & Coffee Booth"
    ],
    "note": "",
    "locations": [
      {
        "location": "Client will provide the address",
        "location_type": "ask"
      }
    ],
    "currency": "CAD",
    "availabilityDays": [
      "Monday",
      "Tuesday",
      "Wednesday",
      "Thursday",
      "Friday",
      "Saturday",
      "Sunday"
    ],
    "startTime": "09:00",
    "endTime": "23:59",
    "eventType": [
      "All"
    ],
    "packageType": "Individual",
    "bookingUrl": "",
    "Sale": "N",
    "New": "N",
    "dateAdded": "07-01-2025",
    "disableGuestsCancelling": true,
    "disableGuestsRescheduling": true,
    "disableCalVideoTranscription": true,
    "disableGuests": true,
    "color": {
      "lightThemeHex": "#292929"
    },
    "minimumBookingNotice": 20160,
    "bookerLayouts": {
      "defaultLayout": "month",
      "enabledLayouts": [
        "month"
      ]
    },
    "bookingFields": [
      {
        "name": "phoneNumber",
        "slug": "phoneNumber",
        "label": "Phone Number",
        "type": "phone",
        "required": true,
        "placeholder": "Please enter your phone number (e.g., +1 123-456-7890)"
      },
      {
        "name": "eventAddress",
        "slug": "eventAddress",
        "label": "Event Address",
        "type": "textarea",
        "required": true,
        "placeholder": "Please enter the full address where the event will take place"
      }
    ],
    "availability": {
      "timeZone": "America/Toronto",
      "schedules": [
        {
          "name": "Availability",
          "timeZone": "America/Toronto",
          "isDefault": true,
          "availability": [
            {
              "days": [
                "Monday",
                "Tuesday",
                "Wednesday",
                "Thursday",
                "Friday",
                "Saturday",
                "Sunday"
              ],
              "startTime": "09:00",
              "endTime": "23:59"
            }
          ]
        }
      ]
    }
  },
  {
    "name": "Waffle Booth",
    "slug": "waffle-booth",
    "price": "50 for 800 | 100 for 1200 | 150 for 1600 | 200 for 2000",
    "description": "",
    "guests": null,
    "maxDuration": 3,
    "servicesIncluded": [
      "Waffle Booth"
    ],
    "equipment": [
      "Waffle Booth"
    ],
    "note": "",
    "locations": [
      {
        "location": "Client will provide the address",
        "location_type": "ask"
      }
    ],
    "currency": "CAD",
    "availabilityDays": [
      "Monday",
      "Tuesday",
      "Wednesday",
      "Thursday",
      "Friday",
      "Saturday",
      "Sunday"
    ],
    "startTime": "09:00",
    "endTime": "23:59",
    "eventType": [
      "All"
    ],
    "packageType": "Individual",
    "bookingUrl": "",
    "Sale": "N",
    "New": "N",
    "dateAdded": "07-01-2025",
    "disableGuestsCancelling": true,
    "disableGuestsRescheduling": true,
    "disableCalVideoTranscription": true,
    "disableGuests": true,
    "color": {
      "lightThemeHex": "#292929"
    },
    "minimumBookingNotice": 20160,
    "bookerLayouts": {
      "defaultLayout": "month",
      "enabledLayouts": [
        "month"
      ]
    },
    "bookingFields": [
      {
        "name": "phoneNumber",
        "slug": "phoneNumber",
        "label": "Phone Number",
        "type": "phone",
        "required": true,
        "placeholder": "Please enter your phone number (e.g., +1 123-456-7890)"
      },
      {
        "name": "eventAddress",
        "slug": "eventAddress",
        "label": "Event Address",
        "type": "textarea",
        "required": true,
        "placeholder": "Please enter the full address where the event will take place"
      }
    ],
    "availability": {
      "timeZone": "America/Toronto",
      "schedules": [
        {
          "name": "Availability",
          "timeZone": "America/Toronto",
          "isDefault": true,
          "availability": [
            {
              "days": [
                "Monday",
                "Tuesday",
                "Wednesday",
                "Thursday",
                "Friday",
                "Saturday",
                "Sunday"
              ],
              "startTime": "09:00",
              "endTime": "23:59"
            }
          ]
        }
      ]
    }
  },
  {
    "name": "Smoothies Booth",
    "slug": "smoothies-booth",
    "price": "50 for 900 | 100 for 1300 | 150 for 1700 | 200 for 2100",
    "description": "",
    "guests": null,
    "maxDuration": 3,
    "servicesIncluded": [
      "Smoothies Booth"
    ],
    "equipment": [
      "Smoothies Booth"
    ],
    "note": "",
    "locations": [
      {
        "location": "Client will provide the address",
        "location_type": "ask"
      }
    ],
    "currency": "CAD",
    "availabilityDays": [
      "Monday",
      "Tuesday",
      "Wednesday",
      "Thursday",
      "Friday",
      "Saturday",
      "Sunday"
    ],
    "startTime": "09:00",
    "endTime": "23:59",
    "eventType": [
      "All"
    ],
    "packageType": "Individual",
    "bookingUrl": "",
    "Sale": "N",
    "New": "N",
    "dateAdded": "07-01-2025",
    "disableGuestsCancelling": true,
    "disableGuestsRescheduling": true,
    "disableCalVideoTranscription": true,
    "disableGuests": true,
    "color": {
      "lightThemeHex": "#292929"
    },
    "minimumBookingNotice": 20160,
    "bookerLayouts": {
      "defaultLayout": "month",
      "enabledLayouts": [
        "month"
      ]
    },
    "bookingFields": [
      {
        "name": "phoneNumber",
        "slug": "phoneNumber",
        "label": "Phone Number",
        "type": "phone",
        "required": true,
        "placeholder": "Please enter your phone number (e.g., +1 123-456-7890)"
      },
      {
        "name": "eventAddress",
        "slug": "eventAddress",
        "label": "Event Address",
        "type": "textarea",
        "required": true,
        "placeholder": "Please enter the full address where the event will take place"
      }
    ],
    "availability": {
      "timeZone": "America/Toronto",
      "schedules": [
        {
          "name": "Availability",
          "timeZone": "America/Toronto",
          "isDefault": true,
          "availability": [
            {
              "days": [
                "Monday",
                "Tuesday",
                "Wednesday",
                "Thursday",
                "Friday",
                "Saturday",
                "Sunday"
              ],
              "startTime": "09:00",
              "endTime": "23:59"
            }
          ]
        }
      ]
    }
  },
  {
    "name": "Sparkler Boxes",
    "slug": "sparkler-boxes",
    "price": "2 for 400 | 4 for 600 | 6 for 800",
    "description": "",
    "guests": null,
    "maxDuration": 1,
    "servicesIncluded": [
      "Sparkler Boxes"
    ],
    "equipment": [
      "Sparkler Boxes"
    ],
    "note": "",
    "locations": [
      {
        "location": "Client will provide the address",
        "location_type": "ask"
      }
    ],
    "currency": "CAD",
    "availabilityDays": [
      "Monday",
      "Tuesday",
      "Wednesday",
      "Thursday",
      "Friday",
      "Saturday",
      "Sunday"
    ],
    "startTime": "09:00",
    "endTime": "23:59",
    "eventType": [
      "All"
    ],
    "packageType": "Individual",
    "bookingUrl": "",
    "Sale": "N",
    "New": "N",
    "dateAdded": "07-01-2025",
    "disableGuestsCancelling": true,
    "disableGuestsRescheduling": true,
    "disableCalVideoTranscription": true,
    "disableGuests": true,
    "color": {
      "lightThemeHex": "#292929"
    },
    "minimumBookingNotice": 20160,
    "bookerLayouts": {
      "defaultLayout": "month",
      "enabledLayouts": [
        "month"
      ]
    },
    "bookingFields": [
      {
        "name": "phoneNumber",
        "slug": "phoneNumber",
        "label": "Phone Number",
        "type": "phone",
        "required": true,
        "placeholder": "Please enter your phone number (e.g., +1 123-456-7890)"
      },
      {
        "name": "eventAddress",
        "slug": "eventAddress",
        "label": "Event Address",
        "type": "textarea",
        "required": true,
        "placeholder": "Please enter the full address where the event will take place"
      }
    ],
    "availability": {
      "timeZone": "America/Toronto",
      "schedules": [
        {
          "name": "Availability",
          "timeZone": "America/Toronto",
          "isDefault": true,
          "availability": [
            {
              "days": [
                "Monday",
                "Tuesday",
                "Wednesday",
                "Thursday",
                "Friday",
                "Saturday",
                "Sunday"
              ],
              "startTime": "09:00",
              "endTime": "23:59"
            }
          ]
        }
      ]
    }
  },
  {
    "name": "Dry Ice Fog",
    "slug": "dry-ice-fog",
    "price": "400",
    "description": "",
    "guests": null,
    "maxDuration": 1,
    "servicesIncluded": [
      "Dry Ice Fog"
    ],
    "equipment": [
      "Dry Ice Fog"
    ],
    "note": "",
    "locations": [
      {
        "location": "Client will provide the address",
        "location_type": "ask"
      }
    ],
    "currency": "CAD",
    "availabilityDays": [
      "Monday",
      "Tuesday",
      "Wednesday",
      "Thursday",
      "Friday",
      "Saturday",
      "Sunday"
    ],
    "startTime": "09:00",
    "endTime": "23:59",
    "eventType": [
      "All"
    ],
    "packageType": "Individual",
    "bookingUrl": "",
    "Sale": "N",
    "New": "N",
    "dateAdded": "07-01-2025",
    "disableGuestsCancelling": true,
    "disableGuestsRescheduling": true,
    "disableCalVideoTranscription": true,
    "disableGuests": true,
    "color": {
      "lightThemeHex": "#292929"
    },
    "minimumBookingNotice": 20160,
    "bookerLayouts": {
      "defaultLayout": "month",
      "enabledLayouts": [
        "month"
      ]
    },
    "bookingFields": [
      {
        "name": "phoneNumber",
        "slug": "phoneNumber",
        "label": "Phone Number",
        "type": "phone",
        "required": true,
        "placeholder": "Please enter your phone number (e.g., +1 123-456-7890)"
      },
      {
        "name": "eventAddress",
        "slug": "eventAddress",
        "label": "Event Address",
        "type": "textarea",
        "required": true,
        "placeholder": "Please enter the full address where the event will take place"
      }
    ],
    "availability": {
      "timeZone": "America/Toronto",
      "schedules": [
        {
          "name": "Availability",
          "timeZone": "America/Toronto",
          "isDefault": true,
          "availability": [
            {
              "days": [
                "Monday",
                "Tuesday",
                "Wednesday",
                "Thursday",
                "Friday",
                "Saturday",
                "Sunday"
              ],
              "startTime": "09:00",
              "endTime": "23:59"
            }
          ]
        }
      ]
    }
  },
  {
    "name": "Laser First Dance",
    "slug": "laser-first-dance",
    "price": "900",
    "description": "",
    "guests": null,
    "maxDuration": 1,
    "servicesIncluded": [
      "Laser First Dance"
    ],
    "equipment": [
      "Laser First Dance"
    ],
    "note": "",
    "locations": [
      {
        "location": "Client will provide the address",
        "location_type": "ask"
      }
    ],
    "currency": "CAD",
    "availabilityDays": [
      "Monday",
      "Tuesday",
      "Wednesday",
      "Thursday",
      "Friday",
      "Saturday",
      "Sunday"
    ],
    "startTime": "09:00",
    "endTime": "23:59",
    "eventType": [
      "All"
    ],
    "packageType": "Individual",
    "bookingUrl": "",
    "Sale": "N",
    "New": "N",
    "dateAdded": "07-01-2025",
    "disableGuestsCancelling": true,
    "disableGuestsRescheduling": true,
    "disableCalVideoTranscription": true,
    "disableGuests": true,
    "color": {
      "lightThemeHex": "#292929"
    },
    "minimumBookingNotice": 20160,
    "bookerLayouts": {
      "defaultLayout": "month",
      "enabledLayouts": [
        "month"
      ]
    },
    "bookingFields": [
      {
        "name": "phoneNumber",
        "slug": "phoneNumber",
        "label": "Phone Number",
        "type": "phone",
        "required": true,
        "placeholder": "Please enter your phone number (e.g., +1 123-456-7890)"
      },
      {
        "name": "eventAddress",
        "slug": "eventAddress",
        "label": "Event Address",
        "type": "textarea",
        "required": true,
        "placeholder": "Please enter the full address where the event will take place"
      }
    ],
    "availability": {
      "timeZone": "America/Toronto",
      "schedules": [
        {
          "name": "Availability",
          "timeZone": "America/Toronto",
          "isDefault": true,
          "availability": [
            {
              "days": [
                "Monday",
                "Tuesday",
                "Wednesday",
                "Thursday",
                "Friday",
                "Saturday",
                "Sunday"
              ],
              "startTime": "09:00",
              "endTime": "23:59"
            }
          ]
        }
      ]
    }
  }
]